LICENSE
MANIFEST.in
README.en.md
README.md
requirements.txt
setup.py
django_template_standalone/__init__.py
django_template_standalone/helper.py
django_template_standalone.egg-info/PKG-INFO
django_template_standalone.egg-info/SOURCES.txt
django_template_standalone.egg-info/dependency_links.txt
django_template_standalone.egg-info/not-zip-safe
django_template_standalone.egg-info/requires.txt
django_template_standalone.egg-info/top_level.txt